CHANGES.rst
MANIFEST.in
README.rst
setup.cfg
setup.py
collective/__init__.py
collective.sendaspdf.egg-info/PKG-INFO
collective.sendaspdf.egg-info/SOURCES.txt
collective.sendaspdf.egg-info/dependency_links.txt
collective.sendaspdf.egg-info/entry_points.txt
collective.sendaspdf.egg-info/namespace_packages.txt
collective.sendaspdf.egg-info/not-zip-safe
collective.sendaspdf.egg-info/requires.txt
collective.sendaspdf.egg-info/top_level.txt
collective/sendaspdf/__init__.py
collective/sendaspdf/config.py
collective/sendaspdf/configure.zcml
collective/sendaspdf/emailer.py
collective/sendaspdf/interfaces.py
collective/sendaspdf/rebuild_i18n.sh
collective/sendaspdf/tests.zcml
collective/sendaspdf/tests_adapter.zcml
collective/sendaspdf/tool.py
collective/sendaspdf/upgrades.py
collective/sendaspdf/utils.py
collective/sendaspdf/Extensions/install.py
collective/sendaspdf/browser/__init__.py
collective/sendaspdf/browser/ajax.py
collective/sendaspdf/browser/base.py
collective/sendaspdf/browser/configure.zcml
collective/sendaspdf/browser/download.py
collective/sendaspdf/browser/realurl.py
collective/sendaspdf/browser/send.py
collective/sendaspdf/browser/css/sendaspdf.css
collective/sendaspdf/browser/jscript/jquery.sendaspdf.js
collective/sendaspdf/browser/templates/ajax.pt
collective/sendaspdf/browser/templates/download.pt
collective/sendaspdf/browser/templates/send_form.pt
collective/sendaspdf/browser/templates/send_page.pt
collective/sendaspdf/exportimport/__init__.py
collective/sendaspdf/exportimport/configure.zcml
collective/sendaspdf/exportimport/setuphandler.py
collective/sendaspdf/locales/collective.sendaspdf.pot
collective/sendaspdf/locales/manual.pot
collective/sendaspdf/locales/en/LC_MESSAGES/collective.sendaspdf.mo
collective/sendaspdf/locales/en/LC_MESSAGES/collective.sendaspdf.po
collective/sendaspdf/locales/fr/LC_MESSAGES/collective.sendaspdf.mo
collective/sendaspdf/locales/fr/LC_MESSAGES/collective.sendaspdf.po
collective/sendaspdf/locales/it/LC_MESSAGES/collective.sendaspdf.mo
collective/sendaspdf/locales/it/LC_MESSAGES/collective.sendaspdf.po
collective/sendaspdf/locales/nl/LC_MESSAGES/collective.sendaspdf.mo
collective/sendaspdf/locales/nl/LC_MESSAGES/collective.sendaspdf.po
collective/sendaspdf/profiles/default/actions.xml
collective/sendaspdf/profiles/default/controlpanel.xml
