Metadata-Version: 1.1
Name: collective.sendaspdf
Version: 3.0
Summary: An open source product for Plone to download or email a page seen by the user as a PDF file.
Home-page: http://github.com/zestsoftware/collective.sendaspdf
Author: Zest Software
Author-email: v.pretre@zestsoftware.nl
License: GPL
Keywords: html pdf converter
Platform: UNKNOWN
Classifier: Framework :: Plone
Classifier: Framework :: Plone :: 3.3
Classifier: Framework :: Plone :: 4.0
Classifier: Framework :: Plone :: 4.1
Classifier: Framework :: Plone :: 4.2
Classifier: Framework :: Plone :: 4.3
Classifier: Programming Language :: Python
Classifier: Programming Language :: Python :: 2.4
Classifier: Programming Language :: Python :: 2.6
Classifier: Programming Language :: Python :: 2.7
